pymake/__init__.py
pymake/__main__.py
pymake/config.py
pymake/pymake.py
pymake/pymake_base.py
pymake/pymake_build_apps.py
pymake/pymake_parser.py
pymake/cmds/__init__.py
pymake/cmds/build.py
pymake/cmds/createjson.py
pymake/cmds/mfpymakecli.py
pymake/plot/__init__.py
pymake/plot/dependency_graphs.py
pymake/utils/_Popen_wrapper.py
pymake/utils/__init__.py
pymake/utils/_compiler_language_files.py
pymake/utils/_compiler_switches.py
pymake/utils/_dag.py
pymake/utils/_file_utils.py
pymake/utils/_meson_build.py
pymake/utils/_usgs_src_update.py
pymake/utils/download.py
pymake/utils/usgsprograms.py
pymake/utils/usgsprograms.txt
mfpymake-1.5.0.dist-info/METADATA
mfpymake-1.5.0.dist-info/WHEEL
mfpymake-1.5.0.dist-info/entry_points.txt
mfpymake-1.5.0.dist-info/licenses/LICENSE.md
mfpymake-1.5.0.dist-info/RECORD
