Metadata-Version: 2.4
Name: mfpymake
Version: 1.5.0
Summary: pymake is a Python package to compile MODFLOW-based models.
Project-URL: Documentation, https://mfpymake.readthedocs.io
Project-URL: Release Notes, https://github.com/modflowpy/flopy/blob/develop/docs/version_changes.md
Project-URL: Bug Tracker, https://github.com/modflowpy/pymake/issues
Project-URL: Source Code, https://github.com/modflowpy/pymake
Author-email: mfpymake Team <modflow@usgs.gov>
Maintainer-email: "Joseph D. Hughes" <jdhughes@usgs.gov>
License: CC0
License-File: LICENSE.md
Keywords: MODFLOW,groundwater,hydrogeology
Classifier: Development Status :: 5 - Production/Stable
Classifier: Intended Audience :: Science/Research
Classifier: License :: CC0 1.0 Universal (CC0 1.0) Public Domain Dedication
Classifier: Programming Language :: Python :: 3 :: Only
Classifier: Programming Language :: Python :: 3.10
Classifier: Programming Language :: Python :: 3.11
Classifier: Programming Language :: Python :: 3.12
Classifier: Programming Language :: Python :: 3.13
Classifier: Topic :: Scientific/Engineering :: Hydrology
Requires-Python: >=3.10
Requires-Dist: meson>=1.8.0
Requires-Dist: networkx
Requires-Dist: ninja
Requires-Dist: numpy
Requires-Dist: pydotplus
Requires-Dist: requests
Provides-Extra: lint
Requires-Dist: cffconvert; extra == 'lint'
Requires-Dist: ruff; extra == 'lint'
Provides-Extra: test
Requires-Dist: appdirs; extra == 'test'
Requires-Dist: cffconvert; extra == 'test'
Requires-Dist: coverage; extra == 'test'
Requires-Dist: filelock; extra == 'test'
Requires-Dist: flaky; extra == 'test'
Requires-Dist: flopy; extra == 'test'
Requires-Dist: matplotlib; extra == 'test'
Requires-Dist: modflow-devtools; extra == 'test'
Requires-Dist: pytest!=8.1.0; extra == 'test'
Requires-Dist: pytest-benchmark; extra == 'test'
Requires-Dist: pytest-cov; extra == 'test'
Requires-Dist: pytest-dependency; extra == 'test'
Requires-Dist: pytest-dotenv; extra == 'test'
Requires-Dist: pytest-xdist; extra == 'test'
Requires-Dist: ruff; extra == 'test'
